t/__init__.py
t/__main__.py
t/common.py
t/extract.py
t/log.py
t/t.py
t/test.py
cbt-0.0.3.dist-info/LICENSE
cbt-0.0.3.dist-info/METADATA
cbt-0.0.3.dist-info/WHEEL
cbt-0.0.3.dist-info/entry_points.txt
cbt-0.0.3.dist-info/top_level.txt
cbt-0.0.3.dist-info/RECORD
