Metadata-Version: 2.1
Name: cbt
Version: 0.0.3
Summary: Auto suggestion english translations cli
Home-page: https://github.com/s045pd/t
Author: s045pd
Author-email: s045pd.x@gmail.com
License: UNKNOWN
Platform: UNKNOWN
Classifier: Programming Language :: Python :: 3.9
Classifier: License :: OSI Approved :: MIT License
Classifier: Operating System :: OS Independent
Classifier: Development Status :: 3 - Alpha
Requires-Python: >=3.9
License-File: LICENSE
Requires-Dist: click (==7.1.2)
Requires-Dist: requests (==2.24.0)
Requires-Dist: requests-html (==0.10.0)
Requires-Dist: termcolor (==1.1.0)
Requires-Dist: prompt-toolkit (==3.0.24)
Requires-Dist: playsound (==1.3.0)
Requires-Dist: PyObjC (==8.1)
